EarlyStopping/L2_boost.py
EarlyStopping/__init__.py
EarlyStopping/conjugate_gradients.py
EarlyStopping/example.py
EarlyStopping/landweber.py
EarlyStopping/regression_tree.py
EarlyStopping/simulation_wrapper.py
EarlyStopping/truncated_svd.py
earlystoppingpy-0.0.4.dist-info/licenses/LICENSE
earlystoppingpy-0.0.4.dist-info/METADATA
earlystoppingpy-0.0.4.dist-info/WHEEL
earlystoppingpy-0.0.4.dist-info/top_level.txt
earlystoppingpy-0.0.4.dist-info/RECORD
