Metadata-Version: 2.4
Name: EarlyStoppingPy
Version: 0.0.4
Summary: EarlyStopping: Implicit Regularisation for Iterative Learning Procedures in Python
Author-email: Eric Ziebell <ziebelle@hu-berlin.de>, Ratmir Miftachov <miftachr@hu-berlin.de>, Bernhard Stankewitz <bstankewitz@posteo.de>, Laura Hucker <huckerla@hu-berlin.de>
License-Expression: MIT
Project-URL: Homepage, https://github.com/EarlyStop/EarlyStopping
Project-URL: Documentation, https://earlystop.github.io/EarlyStopping/
Classifier: Programming Language :: Python :: 3
Classifier: Operating System :: OS Independent
Requires-Python: >=3.7
License-File: LICENSE
Requires-Dist: joblib>=1.3.2
Requires-Dist: matplotlib>=3.8.2
Requires-Dist: numpy>=1.23.5
Requires-Dist: pandas>=1.5.3
Requires-Dist: scikit-learn>=1.4.0
Requires-Dist: scipy>=1.10.1
Requires-Dist: seaborn>=0.13.2
Dynamic: license-file
